wisty/__init__.py
wisty-1.0.0.dist-info/LICENSE
wisty-1.0.0.dist-info/METADATA
wisty-1.0.0.dist-info/WHEEL
wisty-1.0.0.dist-info/entry_points.txt
wisty-1.0.0.dist-info/top_level.txt
wisty-1.0.0.dist-info/RECORD
