Metadata-Version: 2.1
Name: wisty
Version: 1.0.0
Summary: A fast minimal command line tool to download videos hosted on wistia with video id
Home-page: https://github.com/knowbee/wisty.git
Author: Igwaneza Bruce
Author-email: knowbeeinc@gmail.com
Platform: any
Classifier: Environment :: Console
Classifier: Intended Audience :: Developers
Classifier: License :: OSI Approved :: MIT License
Classifier: Operating System :: OS Independent
Classifier: Programming Language :: Python :: 3
Requires-Python: >=3.6
License-File: LICENSE
